Ninja_Preview/Ninja_preview.py
Ninja_Preview/__init__.py
Ninja_Preview/_ninjapreview_resource.py
Ninja_Preview/preview.py
Ninja_Preview-2.2.dist-info/LICENSE
Ninja_Preview-2.2.dist-info/METADATA
Ninja_Preview-2.2.dist-info/WHEEL
Ninja_Preview-2.2.dist-info/entry_points.txt
Ninja_Preview-2.2.dist-info/top_level.txt
Ninja_Preview-2.2.dist-info/RECORD
