Metadata-Version: 2.1
Name: Ninja-Preview
Version: 2.2
Summary: A preview for your Qml files
Home-page: https://github.com/amoh-godwin/Ninja-Preview-wheel/
Author: Amoh - Gyebi Godwin Ampofo Michael
Author-email: amohgyebigodwin@gmail.com
License: UNKNOWN
Project-URL: Bug Tracker, https://github.com/amoh-godwin/Ninja-Preview-wheel/issues/
Project-URL: Documentation, https://github.com/amoh-godwin/Ninja-Preview-wheel/wiki/
Project-URL: Source Code, https://github.com/amoh-godwin/Ninja-Preview-wheel/
Keywords: qmlview,qmlscene,qml,pyqt,pyqt5,pyside,pyside2
Platform: UNKNOWN
Classifier: Programming Language :: Python
Classifier: Programming Language :: Python :: 3
Classifier: Development Status :: 5 - Production/Stable
Classifier: Environment :: Other Environment
Classifier: Intended Audience :: Developers
Classifier: License :: OSI Approved :: GNU Library or Lesser General Public License (LGPL)
Classifier: Operating System :: OS Independent
Classifier: Topic :: Software Development :: Libraries :: Python Modules
Requires-Dist: Qmlview (>=1.1)
